insta/__init__.py
insta/insta.py
insta/instagram/__init__.py
insta/instagram/instagram.py
insta/instagram/stories/Stories.py
insta/instagram/stories/__init__.py
insta_scraper-1.1.7.dist-info/LICENSE
insta_scraper-1.1.7.dist-info/METADATA
insta_scraper-1.1.7.dist-info/WHEEL
insta_scraper-1.1.7.dist-info/entry_points.txt
insta_scraper-1.1.7.dist-info/top_level.txt
insta_scraper-1.1.7.dist-info/RECORD
