Metadata-Version: 2.1
Name: insta-scraper
Version: 1.1.7
Summary: A python tool to download instagram users media.
Home-page: UNKNOWN
Author: Naveen Tummidi
Author-email: naveentummidi0807@gmail.com
License: MIT
Project-URL: Funding, https://donate.pypi.org
Keywords: instagram instagram-scraper
Platform: UNKNOWN
Classifier: Topic :: Software Development :: Libraries
Classifier: Operating System :: OS Independent
Classifier: Development Status :: 5 - Production/Stable
Classifier: License :: OSI Approved :: MIT License
Classifier: Programming Language :: Python :: 2
Classifier: Programming Language :: Python :: 2.7
Requires-Dist: requests
Requires-Dist: bs4
Requires-Dist: wget
Requires-Dist: argparse
